{"oraec2199":{"oraecid":"oraec2199","title":"PT 256 / 〈Westwand〉","date":[{"date":"Teti","id":"JDHTPUAWMZBCZJDBBD2JP4PAD4"}],"origplace":[{"origplace":"Saqqara","id":"YE5ZC7D6LZDTZN2IQKMCRQHW44"}],"objecttype":[{"objecttype":"Grab","id":"HV3JFDDE4NDJ5HTBR7F2QWPHFE"}],"bibliography":"K. Sethe, Die altägyptischen Pyramidentexte, Leipzig 1908-1922 [H];\nJ. P. Allen, The Ancient Egyptian Pyramid Texts, Writings from the Ancient World 23, Atlanta 2005 [Ü]","sentences":[{"token":[{"lineCount":"[T/A/W 15 = 251]","written_form":"ḏ(d)-mdw","cotext_translation":"Worte sprechen; [Rezitationsvermerk]","lemma_form":"ḏd-mdw","lemmaID":"186050","pos":"verb","token":"oraec2199-1-1"}],"translation":"Worte sprechen:"},{"token":[{"lineCount":"[T/A/W 15 = 251]","written_form":"(j)wꜥ.n","cotext_translation":"beerben","lemma_form":"jwꜥ","lemmaID":"22380","pos":"verb","verbalClass":"verb_3-lit","inflection":"suffixConjugation","morphology":"n-morpheme","voice":"active","token":"oraec2199-2-1"},{"lineCount":"[T/A/W 15 = 251]","written_form":"Ttj","cotext_translation":"Teti","lemma_form":"Ttj","lemmaID":"450656","pos":"entity_name","name":"kings_name","token":"oraec2199-2-2"},{"lineCount":"[T/A/W 15 = 251]","written_form":"pn","cotext_translation":"dieser [Dem.Pron. sg.m.]","lemma_form":"pn","lemmaID":"59920","pos":"pronoun","pronoun":"demonstrative_pronoun","token":"oraec2199-2-3"},{"lineCount":"[T/A/W 15 = 251]","written_form":"Gbb","cotext_translation":"Geb","lemma_form":"Gbb","lemmaID":"167010","pos":"entity_name","name":"gods_name","token":"oraec2199-2-4"},{"lineCount":"[T/A/W 15 = 251]","written_form":"(j)wꜥ.n","cotext_translation":"beerben","lemma_form":"jwꜥ","lemmaID":"22380","pos":"verb","verbalClass":"verb_3-lit","inflection":"suffixConjugation","morphology":"n-morpheme","voice":"active","token":"oraec2199-2-5"},{"lineCount":"[T/A/W 15 = 251]","written_form":"Ttj","cotext_translation":"Teti","lemma_form":"Ttj","lemmaID":"450656","pos":"entity_name","name":"kings_name","token":"oraec2199-2-6"},{"lineCount":"[T/A/W 15 = 251]","written_form":"pn","cotext_translation":"dieser [Dem.Pron. sg.m.]","lemma_form":"pn","lemmaID":"59920","pos":"pronoun","pronoun":"demonstrative_pronoun","token":"oraec2199-2-7"},{"lineCount":"[T/A/W 15 = 251]","written_form":"Gbb","cotext_translation":"Geb","lemma_form":"Gbb","lemmaID":"167010","pos":"entity_name","name":"gods_name","token":"oraec2199-2-8"}],"translation":"Dieser Teti hat Geb beerbt, dieser Teti hat Geb beerbt."},{"token":[{"lineCount":"[T/A/W 15 = 251]","written_form":"jw","cotext_translation":"[zur Satzmarkierung und in komplexen Verbformen]","lemma_form":"jw","lemmaID":"21881","pos":"particle","token":"oraec2199-3-1"},{"lineCount":"[T/A/W 15 = 251]","written_form":"(j)wꜥ.n","cotext_translation":"beerben","lemma_form":"jwꜥ","lemmaID":"22380","pos":"verb","verbalClass":"verb_3-lit","inflection":"suffixConjugation","morphology":"n-morpheme","voice":"active","token":"oraec2199-3-2"},{"lineCount":"[T/A/W 15 = 251]","written_form":"Ttj","cotext_translation":"Teti","lemma_form":"Ttj","lemmaID":"450656","pos":"entity_name","name":"kings_name","token":"oraec2199-3-3"},{"lineCount":"[T/A/W 15 = 251]","written_form":"pn","cotext_translation":"dieser [Dem.Pron. sg.m.]","lemma_form":"pn","lemmaID":"59920","pos":"pronoun","pronoun":"demonstrative_pronoun","token":"oraec2199-3-4"},{"lineCount":"[T/A/W 15 = 251]","written_form":"(J)tm(,w)","cotext_translation":"Atum","lemma_form":"Jtm.w","lemmaID":"33040","pos":"entity_name","name":"gods_name","token":"oraec2199-3-5"}],"translation":"Dieser Teti hat Atum beerbt."},{"token":[{"lineCount":"[T/A/W 15 = 251]","written_form":"jw","cotext_translation":"[zur Satzmarkierung und in komplexen Verbformen]","lemma_form":"jw","lemmaID":"21881","pos":"particle","token":"oraec2199-4-1"},{"lineCount":"[T/A/W 15 = 251]","written_form":"Ttj","cotext_translation":"Teti","lemma_form":"Ttj","lemmaID":"450656","pos":"entity_name","name":"kings_name","token":"oraec2199-4-2"},{"lineCount":"[T/A/W 15 = 251]","written_form":"pn","cotext_translation":"dieser [Dem.Pron. sg.m.]","lemma_form":"pn","lemmaID":"59920","pos":"pronoun","pronoun":"demonstrative_pronoun","token":"oraec2199-4-3"},{"lineCount":"[T/A/W 15 = 251]","written_form":"ḥr","cotext_translation":"auf","lemma_form":"ḥr","lemmaID":"107520","pos":"preposition","token":"oraec2199-4-4"},{"lineCount":"[T/A/W 15 = 251]","written_form":"ns,t","cotext_translation":"Thron","lemma_form":"ns.t","lemmaID":"87870","pos":"substantive","numerus":"singular","status":"st_constructus","token":"oraec2199-4-5"},{"lineCount":"[T/A/W 15 = 251]","written_form":"Ḥr,w-sms,w","cotext_translation":"Der ältere Horus","lemma_form":"Ḥr.w-sms.w","lemmaID":"851532","pos":"entity_name","name":"gods_name","token":"oraec2199-4-6"}],"translation":"Dieser Teti ist auf dem Thron des Horsemsu."},{"token":[{"lineCount":"[T/A/W 15 = 251]","written_form":"jw","cotext_translation":"[zur Satzmarkierung und in komplexen Verbformen]","lemma_form":"jw","lemmaID":"21881","pos":"particle","token":"oraec2199-5-1"},{"lineCount":"[T/A/W 15 = 251]","written_form":"jr,t","cotext_translation":"Auge","lemma_form":"jr.t","lemmaID":"28250","pos":"substantive","numerus":"singular","status":"st_constructus","token":"oraec2199-5-2"},{"lineCount":"[T/A/W 15 = 251]","written_form":"Ttj","cotext_translation":"Teti","lemma_form":"Ttj","lemmaID":"450656","pos":"entity_name","name":"kings_name","token":"oraec2199-5-3"},{"lineCount":"[T/A/W 15 = 251]","written_form":"pn","cotext_translation":"dieser [Dem.Pron. sg.m.]","lemma_form":"pn","lemmaID":"59920","pos":"pronoun","pronoun":"demonstrative_pronoun","token":"oraec2199-5-4"},{"lineCount":"[T/A/W 15 = 251]","written_form":"m","cotext_translation":"als (etwas sein)","lemma_form":"m","lemmaID":"64360","pos":"preposition","token":"oraec2199-5-5"},{"lineCount":"[T/A/W 15 = 251]","written_form":"nḫt","cotext_translation":"Stärke","lemma_form":"nḫt.w","lemmaID":"87620","pos":"substantive","numerus":"singular","status":"st_pronominalis","token":"oraec2199-5-6"},{"lineCount":"[T/A/W 15 = 251]","written_form":"=f","cotext_translation":"[Suffix Pron. sg.3.m.]","lemma_form":"=f","lemmaID":"10050","pos":"pronoun","pronoun":"personal_pronoun","token":"oraec2199-5-7"}],"translation":"Das Auge dieses Teti ist seine Stärke."},{"token":[{"lineCount":"[T/A/W 15 = 251]","written_form":"jw","cotext_translation":"[zur Satzmarkierung und in komplexen Verbformen]","lemma_form":"jw","lemmaID":"21881","pos":"particle","token":"oraec2199-6-1"},{"lineCount":"[T/A/W 15 = 251]","written_form":"mk(w),t","cotext_translation":"Schutz","lemma_form":"mkw.t","lemmaID":"76880","pos":"substantive","numerus":"singular","status":"st_constructus","token":"oraec2199-6-2"},{"lineCount":"[T/A/W 15 = 251]","written_form":"Ttj","cotext_translation":"Teti","lemma_form":"Ttj","lemmaID":"450656","pos":"entity_name","name":"kings_name","token":"oraec2199-6-3"},{"lineCount":"[T/A/W 15 = 251]","written_form":"pn","cotext_translation":"dieser [Dem.Pron. sg.m.]","lemma_form":"pn","lemmaID":"59920","pos":"pronoun","pronoun":"demonstrative_pronoun","token":"oraec2199-6-4"},{"lineCount":"[T/A/W 15 = 251]","written_form":"m","cotext_translation":"als (etwas sein)","lemma_form":"m","lemmaID":"64360","pos":"preposition","token":"oraec2199-6-5"},{"lineCount":"[T/A/W 15 = 251]","written_form":"jri̯.yt","cotext_translation":"machen","lemma_form":"jri̯","lemmaID":"851809","pos":"verb","verbalClass":"verb_3-inf","inflection":"participle","genus":"feminine","numerus":"singular","voice":"passive","token":"oraec2199-6-6"},{"lineCount":"[T/A/W 15 = 251]","written_form":"r","cotext_translation":"gegen (Personen); [Opposition]","lemma_form":"r","lemmaID":"91900","pos":"preposition","token":"oraec2199-6-7"},{"lineCount":"[T/A/W 15 = 251]","written_form":"=f","cotext_translation":"[Suffix Pron. sg.3.m.]","lemma_form":"=f","lemmaID":"10050","pos":"pronoun","pronoun":"personal_pronoun","token":"oraec2199-6-8"}],"translation":"Der Schutz dieses Teti besteht in dem, was gegen ihn getan wurde."},{"token":[{"lineCount":"[T/A/W 15 = 251]","written_form":"jw","cotext_translation":"[zur Satzmarkierung und in komplexen Verbformen]","lemma_form":"jw","lemmaID":"21881","pos":"particle","token":"oraec2199-7-1"},{"lineCount":"[T/A/W 15 = 251]","written_form":"nsr","cotext_translation":"Feuer; Flamme","lemma_form":"nsr","lemmaID":"88280","pos":"substantive","numerus":"singular","status":"st_absolutus","genus":"masculine","token":"oraec2199-7-2"},{"lineCount":"[T/A/W 15 = 251]","written_form":"n(,j)","cotext_translation":"von [Genitiv]","lemma_form":"n.j","lemmaID":"850787","pos":"adjective","adjective":"nisbe_adjective_preposition","genus":"masculine","numerus":"singular","token":"oraec2199-7-3"},{"lineCount":"[T/A/W 15 = 251]","written_form":"hh","cotext_translation":"Gluthauch; Hitze","lemma_form":"hh","lemmaID":"99260","pos":"substantive","numerus":"singular","status":"st_absolutus","genus":"masculine","token":"oraec2199-7-4"},{"lineCount":"[T/A/W 15 = 251]","written_form":"n(,j)","cotext_translation":"von [Genitiv]","lemma_form":"n.j","lemmaID":"850787","pos":"adjective","adjective":"nisbe_adjective_preposition","genus":"masculine","numerus":"singular","token":"oraec2199-7-5"},{"lineCount":"[T/A/W 15 = 251]","written_form":"ꜣḫ,t","cotext_translation":"Uräus","lemma_form":"ꜣḫ.t","lemmaID":"220","pos":"substantive","numerus":"singular","status":"st_absolutus","genus":"feminine","token":"oraec2199-7-6"},{"lineCount":"[T/A/W 15 = 251]","written_form":"n.t","cotext_translation":"von [Genitiv]","lemma_form":"n.j","lemmaID":"850787","pos":"adjective","adjective":"nisbe_adjective_preposition","genus":"feminine","numerus":"singular","token":"oraec2199-7-7"},{"lineCount":"[T/A/W 15 = 251]","written_form":"Ttj","cotext_translation":"Teti","lemma_form":"Ttj","lemmaID":"450656","pos":"entity_name","name":"kings_name","token":"oraec2199-7-8"},{"lineCount":"[T/A/W 15 = 251]","written_form":"pn","cotext_translation":"dieser [Dem.Pron. sg.m.]","lemma_form":"pn","lemmaID":"59920","pos":"pronoun","pronoun":"demonstrative_pronoun","token":"oraec2199-7-9"},{"lineCount":"[T/A/W 15 = 251]","written_form":"m","cotext_translation":"als (etwas sein)","lemma_form":"m","lemmaID":"64360","pos":"preposition","token":"oraec2199-7-10"},{"lineCount":"[T/A/W 15 = 251]","written_form":"rnn,wtt","cotext_translation":"Renenutet","lemma_form":"Rnn.wtt","lemmaID":"95190","pos":"entity_name","name":"gods_name","token":"oraec2199-7-11"},{"lineCount":"[T/A/W 15 = 251]","written_form":"tp.t","cotext_translation":"befindlich auf","lemma_form":"tp.j","lemmaID":"171450","pos":"adjective","adjective":"nisbe_adjective_substantive","genus":"feminine","numerus":"singular","token":"oraec2199-7-12"},{"lineCount":"[T/A/W 15 = 251]","written_form":"Ttj","cotext_translation":"Teti","lemma_form":"Ttj","lemmaID":"450656","pos":"entity_name","name":"kings_name","token":"oraec2199-7-13"},{"lineCount":"[T/A/W 15 = 251]","written_form":"pn","cotext_translation":"dieser [Dem.Pron. sg.m.]","lemma_form":"pn","lemmaID":"59920","pos":"pronoun","pronoun":"demonstrative_pronoun","token":"oraec2199-7-14"}],"translation":"Das Feuer des Gluthauchs der Uräusschlange dieses Teti ist das der Renenutet, die auf diesem Teti ist."},{"token":[{"lineCount":"[T/A/W 15 = 251]","written_form":"jw","cotext_translation":"[zur Satzmarkierung und in komplexen Verbformen]","lemma_form":"jw","lemmaID":"21881","pos":"particle","token":"oraec2199-8-1"},{"lineCount":"[T/A/W 15 = 251]","written_form":"dy.n","cotext_translation":"legen; setzen","lemma_form":"wdi̯","lemmaID":"854503","pos":"verb","verbalClass":"verb_irr","inflection":"suffixConjugation","morphology":"n-morpheme","voice":"active","token":"oraec2199-8-2"},{"lineCount":"[T/A/W 15 = 251]","written_form":"Ttj","cotext_translation":"Teti","lemma_form":"Ttj","lemmaID":"450656","pos":"entity_name","name":"kings_name","token":"oraec2199-8-3"},{"lineCount":"[T/A/W 15 = 251]","written_form":"pn","cotext_translation":"dieser [Dem.Pron. sg.m.]","lemma_form":"pn","lemmaID":"59920","pos":"pronoun","pronoun":"demonstrative_pronoun","token":"oraec2199-8-4"},{"lineCount":"[T/A/W 15 = 251]","written_form":"nr,w","cotext_translation":"Schrecken","lemma_form":"nr.w","lemmaID":"85160","pos":"substantive","numerus":"singular","status":"st_pronominalis","token":"oraec2199-8-5"},{"lineCount":"[T/A/W 15 = 251]","written_form":"=f","cotext_translation":"[Suffix Pron. sg.3.m.]","lemma_form":"=f","lemmaID":"10050","pos":"pronoun","pronoun":"personal_pronoun","token":"oraec2199-8-6"},{"lineCount":"[T/A/W 15 = 251]","written_form":"m","cotext_translation":"in","lemma_form":"m","lemmaID":"64360","pos":"preposition","token":"oraec2199-8-7"},{"lineCount":"[T/A/W 15 = 251]","written_form":"jb","cotext_translation":"Herz","lemma_form":"jb","lemmaID":"23290","pos":"substantive","numerus":"singular","status":"st_pronominalis","token":"oraec2199-8-8"},{"lineCount":"[T/A/W 15 = 251]","written_form":"=sn","cotext_translation":"[Suffix Pron. pl.3.c.]","lemma_form":"=sn","lemmaID":"10100","pos":"pronoun","pronoun":"personal_pronoun","token":"oraec2199-8-9"},{"lineCount":"[T/A/W 16 = 252]","written_form":"m","cotext_translation":"[temporal]","lemma_form":"m","lemmaID":"64360","pos":"preposition","token":"oraec2199-8-10"},{"lineCount":"[T/A/W 16 = 252]","written_form":"jri̯.t","cotext_translation":"[idiomat. (mit speziellem Objekt)]","lemma_form":"jri̯","lemmaID":"851809","pos":"verb","verbalClass":"verb_3-inf","inflection":"infinitive","morphology":"t-morpheme","token":"oraec2199-8-11"},{"lineCount":"[T/A/W 16 = 252]","written_form":"ḥꜣꜥ,wt","cotext_translation":"Aufruhr","lemma_form":"ḥꜣꜥ.yt","lemmaID":"101000","pos":"substantive","numerus":"singular","status":"st_absolutus","genus":"feminine","token":"oraec2199-8-12"},{"lineCount":"[T/A/W 16 = 252]","written_form":"jm","cotext_translation":"unter","lemma_form":"m","lemmaID":"64360","pos":"preposition","token":"oraec2199-8-13"},{"lineCount":"[T/A/W 16 = 252]","written_form":"=sn","cotext_translation":"[Suffix Pron. pl.3.c.]","lemma_form":"=sn","lemmaID":"10100","pos":"pronoun","pronoun":"personal_pronoun","token":"oraec2199-8-14"}],"translation":"Dieser Teti hat seinen Schrecken in ihr Herz gegeben, unter ihnen Aufruhr anrichtend."},{"token":[{"lineCount":"[T/A/W 16 = 252]","written_form":"jw","cotext_translation":"[zur Satzmarkierung und in komplexen Verbformen]","lemma_form":"jw","lemmaID":"21881","pos":"particle","token":"oraec2199-9-1"},{"lineCount":"[T/A/W 16 = 252]","written_form":"mꜣ.n","cotext_translation":"sehen","lemma_form":"mꜣꜣ","lemmaID":"66270","pos":"verb","verbalClass":"verb_2-gem","inflection":"suffixConjugation","morphology":"n-morpheme","voice":"active","token":"oraec2199-9-2"},{"lineCount":"[T/A/W 16 = 252]","written_form":"nṯr.pl","cotext_translation":"Gott","lemma_form":"nṯr","lemmaID":"90260","pos":"substantive","numerus":"plural","status":"st_absolutus","token":"oraec2199-9-3"},{"lineCount":"[T/A/W 16 = 252]","written_form":"m","cotext_translation":"in (Zustand)","lemma_form":"m","lemmaID":"64360","pos":"preposition","token":"oraec2199-9-4"},{"lineCount":"[T/A/W 16 = 252]","written_form":"ḥꜣ,wt","cotext_translation":"Nacktheit","lemma_form":"ḥꜣ.yt","lemmaID":"100790","pos":"substantive","numerus":"singular","status":"st_absolutus","genus":"feminine","token":"oraec2199-9-5"}],"translation":"Die Götter haben (es) in Nacktheit gesehen."},{"token":[{"lineCount":"[T/A/W 16 = 252]","written_form":"kss","cotext_translation":"(sich) bücken; (etwas) beugen","lemma_form":"ksi̯","lemmaID":"165430","pos":"verb","verbalClass":"verb_3-inf","inflection":"suffixConjugation","morphology":"geminated","voice":"active","token":"oraec2199-10-1"},{"lineCount":"[T/A/W 16 = 252]","written_form":"=sn","cotext_translation":"[Suffix Pron. pl.3.c.]","lemma_form":"=sn","lemmaID":"10100","pos":"pronoun","pronoun":"personal_pronoun","token":"oraec2199-10-2"},{"lineCount":"[T/A/W 16 = 252]","written_form":"n","cotext_translation":"[Dativ: Richtung]","lemma_form":"n","lemmaID":"78870","pos":"preposition","token":"oraec2199-10-3"},{"lineCount":"[T/A/W 16 = 252]","written_form":"Ttj","cotext_translation":"Teti","lemma_form":"Ttj","lemmaID":"450656","pos":"entity_name","name":"kings_name","token":"oraec2199-10-4"},{"lineCount":"[T/A/W 16 = 252]","written_form":"pn","cotext_translation":"dieser [Dem.Pron. sg.m.]","lemma_form":"pn","lemmaID":"59920","pos":"pronoun","pronoun":"demonstrative_pronoun","token":"oraec2199-10-5"},{"lineCount":"[T/A/W 16 = 252]","written_form":"m","cotext_translation":"in (Zustand)","lemma_form":"m","lemmaID":"64360","pos":"preposition","token":"oraec2199-10-6"},{"lineCount":"[T/A/W 16 = 252]","written_form":"jꜣ","cotext_translation":"Lobpreis","lemma_form":"jꜣ.w","lemmaID":"20360","pos":"substantive","numerus":"singular","status":"st_absolutus","genus":"masculine","token":"oraec2199-10-7"}],"translation":"In Lobpreis verbeugen sie sich vor diesem Teti."},{"token":[{"lineCount":"[T/A/W 16 = 252]","written_form":"ẖnj","cotext_translation":"(jmdn.) fahren; rudern","lemma_form":"ẖni̯","lemmaID":"123230","pos":"verb","verbalClass":"verb_3-inf","inflection":"imperative","numerus":"singular","token":"oraec2199-11-1"},{"lineCount":"[T/A/W 16 = 252]","written_form":"sw","cotext_translation":"ihn [Enkl. Pron. sg.3.m.]","lemma_form":"sw","lemmaID":"129490","pos":"pronoun","pronoun":"personal_pronoun","token":"oraec2199-11-2"},{"lineCount":"[T/A/W 16 = 252]","written_form":"mʾw,t","cotext_translation":"Mutter","lemma_form":"mw.t","lemmaID":"69040","pos":"substantive","numerus":"singular","status":"st_pronominalis","token":"oraec2199-11-3"},{"lineCount":"[T/A/W 16 = 252]","written_form":"=f","cotext_translation":"[Suffix Pron. sg.3.m.]","lemma_form":"=f","lemmaID":"10050","pos":"pronoun","pronoun":"personal_pronoun","token":"oraec2199-11-4"},{"lineCount":"[T/A/W 16 = 252]","written_form":"jtḥ","cotext_translation":"ziehen","lemma_form":"jtḥ","lemmaID":"33410","pos":"verb","verbalClass":"verb_3-lit","inflection":"imperative","numerus":"singular","token":"oraec2199-11-5"},{"lineCount":"[T/A/W 16 = 252]","written_form":"sw","cotext_translation":"ihn [Enkl. Pron. sg.3.m.]","lemma_form":"sw","lemmaID":"129490","pos":"pronoun","pronoun":"personal_pronoun","token":"oraec2199-11-6"},{"lineCount":"[T/A/W 16 = 252]","written_form":"dmj","cotext_translation":"Landestelle","lemma_form":"dmj","lemmaID":"179330","pos":"substantive","numerus":"singular","status":"st_pronominalis","token":"oraec2199-11-7"},{"lineCount":"[T/A/W 16 = 252]","written_form":"=f","cotext_translation":"[Suffix Pron. sg.3.m.]","lemma_form":"=f","lemmaID":"10050","pos":"pronoun","pronoun":"personal_pronoun","token":"oraec2199-11-8"}],"translation":"Rudere ihn, (du) seine Mutter, ziehe/treidele ihn, (du) seine Landestelle."},{"token":[{"lineCount":"[T/A/W 16 = 252]","written_form":"hy","cotext_translation":"(sich) winden","lemma_form":"hy","lemmaID":"97810","pos":"verb","verbalClass":"verb_2-lit","inflection":"imperative","numerus":"singular","token":"oraec2199-12-1"},{"lineCount":"[T/A/W 16 = 252]","written_form":"nwḥ","cotext_translation":"Seil (allg.)","lemma_form":"nwḥ","lemmaID":"81400","pos":"substantive","status":"st_pronominalis","numerus":"singular","token":"oraec2199-12-2"},{"lineCount":"[T/A/W 16 = 252]","written_form":"=k","cotext_translation":"[Suffix Pron. sg.2.m.]","lemma_form":"=k","lemmaID":"10110","pos":"pronoun","pronoun":"personal_pronoun","token":"oraec2199-12-3"}],"translation":"Winde dein Seil."}],"credits":{"license":"cc-by-sa-4.0","author":"Doris Topmann","source":["https://github.com/simondschweitzer/aes","https://github.com/simondschweitzer/aed-tei/blob/master/files/RJ4JDHM6AVDXJM2RZWIJ3TCPPA.xml"]}}}