{"oraec1926":{"oraecid":"oraec1926","title":"Tb 035 / pTurin Museo Egizio 1791 Tb 1-113","date":[{"date":"Makedonen, Ptolemäer","id":"HYYNMJRFTVFIHB7JUA6M2QW3LQ"}],"origplace":[{"origplace":"Theben","id":"RGS2OLARZRFTHEFGRYNKB6YJ5E"}],"objecttype":[{"objecttype":"Schriftrolle","id":"5QIW3ZRHQFGINHBP4GI2GI4LFA"}],"location":[{"location":"Turin","id":"J7JAWOYU7NGJHG7RFSID7PTQP4"}],"idno":["1791","1791"],"bibliography":"Lepsius, Das Todtenbuch der Ägypter, Leipzig 1842 (Neudruck Osnabrück 1969)\n\nB. de Rachewiltz, Il Libro dei Morti, Mailand 1958 (P, Ü)\n\nH.A. Legowski/M. Müller-Roth, Papyrus Turin 1791 - revisited (in Vorb. für Göttinger Miszellen). Zahlreiche Korrekturen der Lesungen von Lepsius. Ich danke den Autoren für Einsicht in eine vorläufige Fassung ihres Manuskripts im Oktober 2012, die ca. 20 Korrekturen der TLA-Daten zu pTurin 1791 ermöglichte.","sentences":[{"token":[{"lineCount":" [Titelzeile]","written_form":"rʾ","cotext_translation":"Spruch","lemma_form":"rʾ","lemmaID":"92560","pos":"substantive","numerus":"substantive_masc","token":"oraec1926-1-1"},{"lineCount":" [Titelzeile]","written_form":"n","cotext_translation":"[Gen.]","lemma_form":"n.j","lemmaID":"850787","pos":"adjective","adjective":"nisbe_adjective_preposition","token":"oraec1926-1-2"},{"lineCount":" [Titelzeile]","written_form":"tm","cotext_translation":"[Negationsverb]","lemma_form":"tm","lemmaID":"854578","pos":"verb","verbalClass":"verb_2-lit","token":"oraec1926-1-3"},{"lineCount":" [Titelzeile]","written_form":"rḏi̯.t","cotext_translation":"veranlassen (daß)","lemma_form":"rḏi̯","lemmaID":"851711","pos":"verb","verbalClass":"verb_irr","token":"oraec1926-1-4"},{"lineCount":" [Titelzeile]","written_form":"wnm.tw","cotext_translation":"fressen","lemma_form":"wnm","lemmaID":"46710","pos":"verb","verbalClass":"verb_3-lit","token":"oraec1926-1-5"},{"lineCount":" [Titelzeile]","written_form":"z","cotext_translation":"Mann","lemma_form":"z","lemmaID":"125010","pos":"substantive","numerus":"substantive_masc","token":"oraec1926-1-6"},{"lineCount":" [Titelzeile]","written_form":"m","cotext_translation":"in, zu, an, aus [lokal]","lemma_form":"m","lemmaID":"64360","pos":"preposition","token":"oraec1926-1-7"},{"lineCount":" [Titelzeile]","written_form":"⸢ẖr-nṯr⸣","cotext_translation":"Nekropole, Totenreich","lemma_form":"ẖr.t-nṯr","lemmaID":"500066","pos":"substantive","token":"oraec1926-1-8"},{"lineCount":" [Titelzeile]","written_form":"j[n]","cotext_translation":"durch, seitens jmds.","lemma_form":"jn","lemmaID":"26660","pos":"preposition","token":"oraec1926-1-9"},{"lineCount":" [Titelzeile]","written_form":"[ḥfꜣ,w].pl","cotext_translation":"Schlange","lemma_form":"ḥfꜣ.w","lemmaID":"104390","pos":"substantive","numerus":"substantive_masc","token":"oraec1926-1-10"}],"translation":"Spruch, um nicht zuzulassen, daß ein Mann im Totenreich von [Schlang]en gefressen wird."},{"token":[{"lineCount":" [1]","written_form":"ḏd-mdw","cotext_translation":"Worte sprechen","lemma_form":"ḏd-mdw","lemmaID":"186050","pos":"verb","token":"oraec1926-2-1"},{"lineCount":" [1]","written_form":"jn","cotext_translation":"durch, seitens jmds.","lemma_form":"jn","lemmaID":"26660","pos":"preposition","token":"oraec1926-2-2"},{"lineCount":" [1]","written_form":"Wsjr","cotext_translation":"[Totentitel]","lemma_form":"Wsjr","lemmaID":"49461","pos":"epitheton_title","epitheton":"title","token":"oraec1926-2-3"},{"written_form":"[...]","token":"oraec1926-2-4"},{"lineCount":" [1]","written_form":"mꜣꜥ-ḫrw","cotext_translation":"gerechtfertigt, Seliger","lemma_form":"mꜣꜥ-ḫrw","lemmaID":"66750","pos":"substantive","token":"oraec1926-2-5"}],"translation":"Von Osiris NN, gerechtfertigt, zu sprechen:"},{"token":[{"lineCount":" [1]","written_form":"j","cotext_translation":"[Interjektion]; oh!","lemma_form":"j","lemmaID":"20030","pos":"interjection","token":"oraec1926-3-1"},{"lineCount":" [1]","written_form":"Šw","cotext_translation":"GN/Schu","lemma_form":"Šw","lemmaID":"152710","pos":"entity_name","name":"gods_name","token":"oraec1926-3-2"},{"lineCount":" [1]","written_form":"j.n","cotext_translation":"sagen","lemma_form":"j","lemmaID":"500024","pos":"verb","token":"oraec1926-3-3"},{"lineCount":" [1]","written_form":"⸮Ḏd,w(j)?","cotext_translation":"[Gott]","lemma_form":"ḏd.wj","lemmaID":"185990","pos":"epitheton_title","epitheton":"epith_god","token":"oraec1926-3-4"},{"lineCount":" [1]","written_form":"ṯz-pẖr","cotext_translation":"[Rezitationsvermerk]","lemma_form":"ṯꜣz-pẖr","lemmaID":"177140","pos":"undefined","token":"oraec1926-3-5"},{"lineCount":" [1]","written_form":"ẖr,j","cotext_translation":"befindlich unter, unterer","lemma_form":"ẖr.j","lemmaID":"124220","pos":"adjective","adjective":"nisbe_adjective_preposition","token":"oraec1926-3-6"},{"lineCount":" [1]","written_form":"ꜥfn,t","cotext_translation":"Kopftuch","lemma_form":"ꜥfn.t","lemmaID":"37400","pos":"substantive","numerus":"substantive_fem","token":"oraec1926-3-7"},{"lineCount":" [1]","written_form":"n.t","cotext_translation":"[Gen.]","lemma_form":"n.j","lemmaID":"850787","pos":"adjective","adjective":"nisbe_adjective_preposition","token":"oraec1926-3-8"},{"lineCount":" [1]","written_form":"Ḥw,t-Ḥr,w","cotext_translation":"GN/Hathor","lemma_form":"Ḥw.t-Ḥr.w","lemmaID":"99960","pos":"entity_name","name":"gods_name","token":"oraec1926-3-9"}],"translation":"\"Oh Schu!\", sagt der Busirit(?) - und umgekehrt -, der das Kopftuch der Hathor trägt."},{"token":[{"lineCount":" [1]","written_form":"ḫnmm","cotext_translation":"erfreuen","lemma_form":"ḫnm","lemmaID":"854533","pos":"verb","verbalClass":"verb_3-lit","token":"oraec1926-4-1"},{"lineCount":" [1]","written_form":"=sn","cotext_translation":"sie [pron. suff. 3. pl.]","lemma_form":"=sn","lemmaID":"10100","pos":"pronoun","pronoun":"personal_pronoun","token":"oraec1926-4-2"},{"lineCount":" [1]","written_form":"Wsjr","cotext_translation":"GN/Osiris","lemma_form":"Wsjr","lemmaID":"49460","pos":"entity_name","name":"gods_name","token":"oraec1926-4-3"},{"lineCount":" [1]","written_form":"j.n","cotext_translation":"sagen","lemma_form":"j","lemmaID":"500024","pos":"verb","token":"oraec1926-4-4"},{"lineCount":" [1]","written_form":"wnm","cotext_translation":"essen","lemma_form":"wnm","lemmaID":"46710","pos":"verb","verbalClass":"verb_3-lit","token":"oraec1926-4-5"},{"lineCount":" [2]","written_form":"tʾ.pl","cotext_translation":"Brot (allgem. Ausdruck)","lemma_form":"tʾ","lemmaID":"168810","pos":"substantive","numerus":"substantive_masc","token":"oraec1926-4-6"},{"lineCount":" [2]","written_form":"=f","cotext_translation":"er [pron. suff. 3. masc. sg.]","lemma_form":"=f","lemmaID":"10050","pos":"pronoun","pronoun":"personal_pronoun","token":"oraec1926-4-7"}],"translation":"\"Sie erfreuen Osiris\", sagt der Esser seiner Brote."},{"token":[{"lineCount":" [2]","written_form":"sḫdi̯","cotext_translation":"stromab fahren lassen","lemma_form":"sḫdi̯","lemmaID":"143260","pos":"verb","verbalClass":"verb_caus_3-inf","token":"oraec1926-5-1"},{"lineCount":" [2]","written_form":"nhꜣ,pl","cotext_translation":"böse(?) Gottheit(en)","lemma_form":"Nhꜣ.w","lemmaID":"85350","pos":"entity_name","name":"gods_name","token":"oraec1926-5-2"},{"lineCount":" [2]","written_form":"zp-2","cotext_translation":"['zweimal' als Leseanweisung]","lemma_form":"zp-2","lemmaID":"70011","pos":"substantive","token":"oraec1926-5-3"}],"translation":"Fahre die \"Niedergeschlagenen\" stromab - zweimal!"},{"token":[{"lineCount":" [2]","written_form":"Wsjr","cotext_translation":"[Totentitel]","lemma_form":"Wsjr","lemmaID":"49461","pos":"epitheton_title","epitheton":"title","token":"oraec1926-6-1"},{"written_form":"[...]","token":"oraec1926-6-2"},{"lineCount":" [2]","written_form":"mꜣꜥ-ḫrw","cotext_translation":"gerechtfertigt, Seliger","lemma_form":"mꜣꜥ-ḫrw","lemmaID":"66750","pos":"substantive","token":"oraec1926-6-3"},{"lineCount":" [2]","written_form":"zni̯","cotext_translation":"etw. passieren","lemma_form":"zni̯","lemmaID":"854546","pos":"verb","verbalClass":"verb_3-inf","token":"oraec1926-6-4"},{"lineCount":" [2]","written_form":"sw","cotext_translation":"er, [pron. enkl. 3. masc. sg.]","lemma_form":"sw","lemmaID":"129490","pos":"pronoun","pronoun":"personal_pronoun","token":"oraec1926-6-5"},{"lineCount":" [2]","written_form":"rʾ","cotext_translation":"Öffnung, Tür","lemma_form":"rʾ","lemmaID":"92560","pos":"substantive","numerus":"substantive_masc","token":"oraec1926-6-6"}],"translation":"\"Osiris NN, gerechtfertigt, passiere ihn, den Eingang (?)!"},{"token":[{"lineCount":" [2]","written_form":"zni̯.n","cotext_translation":"etw. passieren","lemma_form":"zni̯","lemmaID":"854546","pos":"verb","verbalClass":"verb_3-inf","token":"oraec1926-7-1"},{"lineCount":" [2]","written_form":"n","cotext_translation":"wegen [Grund, Zweck]","lemma_form":"n","lemmaID":"78870","pos":"preposition","token":"oraec1926-7-2"},{"lineCount":" [2]","written_form":"=k","cotext_translation":"du [pron. suff. 2. masc. sg.]","lemma_form":"=k","lemmaID":"10110","pos":"pronoun","pronoun":"personal_pronoun","token":"oraec1926-7-3"},{"lineCount":" [2]","written_form":"sw","cotext_translation":"er, [pron. enkl. 3. masc. sg.]","lemma_form":"sw","lemmaID":"129490","pos":"pronoun","pronoun":"personal_pronoun","token":"oraec1926-7-4"},{"lineCount":" [2]","written_form":"zk","cotext_translation":"[Bez. e. Schlange]","lemma_form":"zkzk","lemmaID":"146970","pos":"substantive","numerus":"substantive_masc","token":"oraec1926-7-5"},{"lineCount":" [2]","written_form":"j.n","cotext_translation":"sagen","lemma_form":"j","lemmaID":"500024","pos":"verb","token":"oraec1926-7-6"},{"lineCount":" [2]","written_form":"sꜥm.pl","cotext_translation":"[offizinell verwendete Pflanze]","lemma_form":"sꜥm","lemmaID":"128870","pos":"substantive","numerus":"substantive_masc","token":"oraec1926-7-7"}],"translation":"Deinetwegen hat ihn (schon) die zk-Schlange passiert\", sagen sie, die sꜥm-Pflanzen."},{"token":[{"lineCount":" [3]","written_form":"zꜣw","cotext_translation":"sich hüten, achten auf","lemma_form":"zꜣu̯","lemmaID":"126290","pos":"verb","verbalClass":"verb_3-inf","token":"oraec1926-8-1"},{"lineCount":" [3]","written_form":"ṯw","cotext_translation":"du, [pron. enkl. 2. masc. sg.]","lemma_form":"ṯw","lemmaID":"174900","pos":"pronoun","pronoun":"personal_pronoun","token":"oraec1926-8-2"},{"lineCount":" [3]","written_form":"r","cotext_translation":"gegen (Personen), zum (Lohn) [Richtg., Zweck]","lemma_form":"r","lemmaID":"91900","pos":"preposition","token":"oraec1926-8-3"},{"lineCount":" [3]","written_form":"jqr.pl","cotext_translation":"[Lebensmittel]","lemma_form":"jqrt","lemmaID":"32320","pos":"substantive","token":"oraec1926-8-4"}],"translation":"\"Hüte dich vor den iqr-Pflanzen!\""},{"token":[{"lineCount":" [3]","written_form":"Wsjr","cotext_translation":"GN/Osiris","lemma_form":"Wsjr","lemmaID":"49460","pos":"entity_name","name":"gods_name","token":"oraec1926-9-1"},{"lineCount":" [3]","written_form":"pw{y}","cotext_translation":"[im Nominalsatz]","lemma_form":"pw","lemmaID":"851517","pos":"pronoun","pronoun":"demonstrative_pronoun","token":"oraec1926-9-2"},{"lineCount":" [3]","written_form":"nn","cotext_translation":"Dieses, [pron. dem.]","lemma_form":"nn","lemmaID":"851523","pos":"pronoun","pronoun":"demonstrative_pronoun","token":"oraec1926-9-3"},{"lineCount":" [3]","written_form":"dbḥ","cotext_translation":"bedürfen","lemma_form":"dbḥ","lemmaID":"178750","pos":"verb","verbalClass":"verb_3-lit","token":"oraec1926-9-4"},{"lineCount":" [3]","written_form":"qrs","cotext_translation":"Begräbnis","lemma_form":"qrs","lemmaID":"161950","pos":"substantive","numerus":"substantive_masc","token":"oraec1926-9-5"}],"translation":"Diese sind Osiris, der der Bestattung bedarf."},{"token":[{"lineCount":" [3]","written_form":"ḫr.n","cotext_translation":"fallen","lemma_form":"ḫr","lemmaID":"119610","pos":"verb","verbalClass":"verb_2-lit","token":"oraec1926-10-1"},{"lineCount":" [3]","written_form":"jr,t.pl","cotext_translation":"Auge","lemma_form":"jr.t","lemmaID":"28250","pos":"substantive","numerus":"substantive_fem","token":"oraec1926-10-2"},{"lineCount":" [3]","written_form":"wr","cotext_translation":"Großer, Fürst","lemma_form":"wr","lemmaID":"47280","pos":"substantive","numerus":"substantive_masc","token":"oraec1926-10-3"}],"translation":"Die Augen des Großen sind gefallen (?)."},{"token":[{"lineCount":" [3]","written_form":"ḥnw,t.j","cotext_translation":"Horn","lemma_form":"ḥnw.t","lemmaID":"106370","pos":"substantive","numerus":"substantive_fem","token":"oraec1926-11-1"},{"lineCount":" [3]","written_form":"=f","cotext_translation":"er [pron. suff. 3. masc. sg.]","lemma_form":"=f","lemmaID":"10050","pos":"pronoun","pronoun":"personal_pronoun","token":"oraec1926-11-2"},{"lineCount":" [3]","written_form":"n","cotext_translation":"zu, für, an [Richtung]; [Dat.]","lemma_form":"n","lemmaID":"78870","pos":"preposition","token":"oraec1926-11-3"},{"lineCount":" [3]","written_form":"=k","cotext_translation":"du [pron. suff. 2. masc. sg.]","lemma_form":"=k","lemmaID":"10110","pos":"pronoun","pronoun":"personal_pronoun","token":"oraec1926-11-4"}],"translation":"Sein Hörnerpaar gehört dir."},{"token":[{"lineCount":" [3]","written_form":"pš","cotext_translation":"teilen","lemma_form":"psš","lemmaID":"62280","pos":"verb","verbalClass":"verb_3-lit","token":"oraec1926-12-1"},{"lineCount":" [3]","written_form":"=f","cotext_translation":"er [pron. suff. 3. masc. sg.]","lemma_form":"=f","lemmaID":"10050","pos":"pronoun","pronoun":"personal_pronoun","token":"oraec1926-12-2"},{"lineCount":" [3]","written_form":"mꜣꜥ,t","cotext_translation":"Rechtes, Wahrheit","lemma_form":"mꜣꜥ.t","lemmaID":"66620","pos":"substantive","numerus":"substantive_fem","token":"oraec1926-12-3"},{"lineCount":" [3]","written_form":"m","cotext_translation":"mittels, durch [instr.]","lemma_form":"m","lemmaID":"64360","pos":"preposition","token":"oraec1926-12-4"},{"lineCount":" [3]","written_form":"wḏꜥ","cotext_translation":"trennen, richten, zuweisen","lemma_form":"wḏꜥ","lemmaID":"52360","pos":"verb","verbalClass":"verb_3-lit","token":"oraec1926-12-5"},{"lineCount":" [3]","written_form":"ꜥḥꜥ,w.pl","cotext_translation":"Standort; Stellung","lemma_form":"ꜥḥꜥ.w","lemmaID":"40410","pos":"substantive","numerus":"substantive_masc","token":"oraec1926-12-6"}],"translation":"Er verteilt als Urteil (über) Positionen Maat."}],"credits":{"license":"cc-by-sa-4.0","author":"Burkhard Backes","source":["https://github.com/simondschweitzer/aes","https://github.com/simondschweitzer/aed-tei/blob/master/files/R3RBEOIKBVDDVK7WPMNID3DO5E.xml"]}}}